README.md
setup.cfg
setup.py
syncanyserver/__init__.py
syncanyserver/database.py
syncanyserver/main.py
syncanyserver/server.py
syncanyserver/table.py
syncanyserver/user.py
syncanyserver.egg-info/PKG-INFO
syncanyserver.egg-info/SOURCES.txt
syncanyserver.egg-info/dependency_links.txt
syncanyserver.egg-info/entry_points.txt
syncanyserver.egg-info/not-zip-safe
syncanyserver.egg-info/requires.txt
syncanyserver.egg-info/top_level.txt
syncanyserver/filters/__init__.py
syncanyserver/schema/__init__.py
syncanyserver/schema/loader.py
syncanyserver/schema/mongo_loader.py
syncanyserver/schema/mysql_loader.py